{
  "Services_and_Utilities": [
    "Bee Egypt",
    "Cairo Electricity Distribution Company",
    "Cairo Water and Sanitation",
    "EG Pay",
    "Etisalat Egypt (e&)",
    "Fawry",
    "Masary",
    "Netflix Egypt",
    "Orange Egypt",
    "Shahid VIP",
    "Spotify Egypt",
    "Telecom Egypt Landline",
    "Vodafone Egypt",
    "WE Internet Billing",
    "We Telecom Egypt"
  ],
  "Transportation": [
    "Cairo Metro CTA",
    "Cairo Monorail NRCA",
    "Careem Egypt",
    "DiDi Egypt",
    "Nile Taxi",
    "OTA Uber Moto",
    "Robusta Cab",
    "Swvl Egypt",
    "Uber Egypt",
    "inDrive Egypt"
  ],
  "Food_and_Dining": [
    "Burger King Egypt",
    "Butcher's Burger",
    "Cilantro Cafe",
    "Dunkin Egypt",
    "Elmenus",
    "Hardee's Egypt",
    "KFC Egypt",
    "Kazoku Sushi",
    "Koshary El Tahrir",
    "Lucille's",
    "McDonald's Egypt",
    "Mo'men",
    "Otlob",
    "Ovio Cafe",
    "Palmyra Restaurant",
    "Pizza Hut Egypt",
    "Sequoia Restaurant",
    "Talabat EG",
    "The Grill at Four Seasons",
    "Zooba"
  ],
  "Travel": [
    "Ain Sokhna Road Toll",
    "Banha Road Toll NUCA",
    "E-Asphalt Naguib",
    "GTS Bus Egypt",
    "Go Bus Egypt"
  ],
  "Shopping": [
    "Amazon.eg",
    "Azadea Group Egypt",
    "Cairo Festival City Mall",
    "City Stars Mall",
    "Concrete Egypt",
    "Decathlon Egypt",
    "H&M Egypt",
    "IKEA Egypt",
    "Jumia Egypt",
    "LC Waikiki Egypt",
    "Mall of Arabia",
    "Mall of Egypt",
    "Max Fashion Egypt",
    "Mobaco",
    "Noon Egypt",
    "Point 90 Mall",
    "Ragab Sons",
    "Sigma Sporting Goods",
    "Virgin Megastore Egypt",
    "Zara Egypt"
  ],
  "Groceries": [
    "BIM Egypt",
    "Breadfast",
    "Carrefour Egypt",
    "El Abd Supermarket",
    "El Nakheel Supermarket",
    "Fathalla Market",
    "Gourmet Egypt",
    "Hyper One",
    "Kazyon Market",
    "Kheir Zaman",
    "Majid Al Futtaim Hypermarket",
    "Metro Markets",
    "Oscar Supermarket",
    "Seoudi Market",
    "Spinneys Egypt"
  ],
  "Freelance_Work": [
    "Contra",
    "Fiverr",
    "Freelancer.com",
    "Guru",
    "Khamsat",
    "Malt",
    "Mostaql",
    "PeoplePerHour",
    "Toptal",
    "Upwork"
  ],
  "Health_and_Pharmacy": [
    "19th Pharmacy",
    "Al Moasher Pharmacy",
    "Almouneer Diabetes Care",
    "Andalusia Hospitals",
    "As-Salam International Hospital",
    "Aster Pharmacy Egypt",
    "Ateyat Pharmacy",
    "Cairo Medical Center",
    "Cairo Pharmacy",
    "Cleopatra Hospital",
    "Dar Al Fouad Hospital",
    "El Dawlia Pharmacy",
    "El Ezaby Pharmacy",
    "Seif Pharmacy",
    "Vezeeta"
  ],
  "Entertainment": [
    "Al Ahly Club",
    "Cairo Festival City IMAX",
    "Cairo Opera House",
    "Cinemark Egypt",
    "Dream Park",
    "El Gezira Sporting Club",
    "Escape Rooms Egypt",
    "Kidzania Cairo",
    "Magic Planet Egypt",
    "Renaissance Cinemas",
    "Sky Zone Cairo",
    "Ticketmix EG",
    "VOX Cinemas Egypt",
    "Wadi Degla Club",
    "Xcite Egypt"
  ],
  "Salary_and_Income": [
    "Arab African International Bank Payroll",
    "Arab Bank Egypt Payroll",
    "Banque Misr Salary",
    "CIB Payroll Transfer",
    "Egypt Post Salary",
    "Etisalat Egypt Payroll",
    "Fawry Pay Received",
    "HSBC Egypt Salary Credit",
    "InstaPay Transfer",
    "Ministry of Finance Salary WPS",
    "NBE Payroll Credit",
    "Orange Money Received",
    "QNB Egypt Payroll",
    "Telecom Egypt Payroll",
    "Vodafone Cash Received"
  ]
}